{"regionS":[{"loaded":false,"idRegion":0,"isVisitedRegion":false,"visitedPoints":99,"numberOfPoints":99,"levelOfRegion":99,"typeOfRegion":"Wild","structType":0,"structVariant":[99,99,99,99,99,99],"points":[]},{"loaded":false,"idRegion":1,"isVisitedRegion":false,"visitedPoints":99,"numberOfPoints":99,"levelOfRegion":99,"typeOfRegion":"Wild","structType":0,"structVariant":[99,99,99,99,99,99],"points":[]},{"loaded":false,"idRegion":2,"isVisitedRegion":false,"visitedPoints":99,"numberOfPoints":99,"levelOfRegion":99,"typeOfRegion":"Wild","structType":0,"structVariant":[99,99,99,99,99,99],"points":[]},{"loaded":false,"idRegion":3,"isVisitedRegion":false,"visitedPoints":99,"numberOfPoints":99,"levelOfRegion":99,"typeOfRegion":"Wild","structType":0,"structVariant":[99,99,99,99,99,99],"points":[]},{"loaded":false,"idRegion":4,"isVisitedRegion":true,"visitedPoints":99,"numberOfPoints":22,"levelOfRegion":99,"typeOfRegion":"Wild","structType":0,"structVariant":[0,2,1,2,0,0],"points":[{"Xpos":4.5,"Ypos":2.5,"isVisitedPoint":false,"isPossibleToMove":false,"isExplorerOnMe":false,"canGoUp":false,"canGoDown":false,"canGoRight":false,"canGoLeft":true,"levelOfPoint":0},{"Xpos":3.5,"Ypos":2.5,"isVisitedPoint":false,"isPossibleToMove":false,"isExplorerOnMe":false,"canGoUp":false,"canGoDown":false,"canGoRight":true,"canGoLeft":true,"levelOfPoint":0},{"Xpos":3.5,"Ypos":1.5,"isVisitedPoint":false,"isPossibleToMove":false,"isExplorerOnMe":false,"canGoUp":false,"canGoDown":true,"canGoRight":false,"canGoLeft":false,"levelOfPoint":0},{"Xpos":2.5,"Ypos":2.5,"isVisitedPoint":false,"isPossibleToMove":false,"isExplorerOnMe":false,"canGoUp":false,"canGoDown":true,"canGoRight":true,"canGoLeft":true,"levelOfPoint":0},{"Xpos":1.5,"Ypos":2.5,"isVisitedPoint":false,"isPossibleToMove":false,"isExplorerOnMe":false,"canGoUp":false,"canGoDown":false,"canGoRight":true,"canGoLeft":true,"levelOfPoint":0},{"Xpos":2.5,"Ypos":1.5,"isVisitedPoint":false,"isPossibleToMove":false,"isExplorerOnMe":false,"canGoUp":true,"canGoDown":false,"canGoRight":false,"canGoLeft":false,"levelOfPoint":0},{"Xpos":1.5,"Ypos":1.5,"isVisitedPoint":false,"isPossibleToMove":false,"isExplorerOnMe":false,"canGoUp":false,"canGoDown":true,"canGoRight":false,"canGoLeft":false,"levelOfPoint":0},{"Xpos":0.5,"Ypos":2.5,"isVisitedPoint":false,"isPossibleToMove":false,"isExplorerOnMe":false,"canGoUp":false,"canGoDown":true,"canGoRight":true,"canGoLeft":true,"levelOfPoint":0},{"Xpos":-0.5,"Ypos":2.5,"isVisitedPoint":false,"isPossibleToMove":false,"isExplorerOnMe":false,"canGoUp":false,"canGoDown":true,"canGoRight":true,"canGoLeft":false,"levelOfPoint":0},{"Xpos":0.5,"Ypos":1.5,"isVisitedPoint":false,"isPossibleToMove":false,"isExplorerOnMe":false,"canGoUp":true,"canGoDown":true,"canGoRight":false,"canGoLeft":false,"levelOfPoint":0},{"Xpos":-0.5,"Ypos":1.5,"isVisitedPoint":false,"isPossibleToMove":false,"isExplorerOnMe":false,"canGoUp":true,"canGoDown":false,"canGoRight":false,"canGoLeft":false,"levelOfPoint":0},{"Xpos":3.5,"Ypos":0.5,"isVisitedPoint":false,"isPossibleToMove":false,"isExplorerOnMe":false,"canGoUp":true,"canGoDown":true,"canGoRight":false,"canGoLeft":false,"levelOfPoint":0},{"Xpos":4.5,"Ypos":-0.5,"isVisitedPoint":false,"isPossibleToMove":false,"isExplorerOnMe":false,"canGoUp":false,"canGoDown":false,"canGoRight":false,"canGoLeft":true,"levelOfPoint":0},{"Xpos":3.5,"Ypos":-0.5,"isVisitedPoint":false,"isPossibleToMove":false,"isExplorerOnMe":false,"canGoUp":true,"canGoDown":false,"canGoRight":true,"canGoLeft":true,"levelOfPoint":0},{"Xpos":2.5,"Ypos":0.5,"isVisitedPoint":false,"isPossibleToMove":false,"isExplorerOnMe":false,"canGoUp":false,"canGoDown":true,"canGoRight":false,"canGoLeft":false,"levelOfPoint":0},{"Xpos":1.5,"Ypos":0.5,"isVisitedPoint":false,"isPossibleToMove":false,"isExplorerOnMe":false,"canGoUp":true,"canGoDown":true,"canGoRight":false,"canGoLeft":false,"levelOfPoint":0},{"Xpos":2.5,"Ypos":-0.5,"isVisitedPoint":false,"isPossibleToMove":false,"isExplorerOnMe":false,"canGoUp":true,"canGoDown":false,"canGoRight":true,"canGoLeft":true,"levelOfPoint":0},{"Xpos":1.5,"Ypos":-0.5,"isVisitedPoint":false,"isPossibleToMove":false,"isExplorerOnMe":false,"canGoUp":true,"canGoDown":false,"canGoRight":true,"canGoLeft":true,"levelOfPoint":0},{"Xpos":0.5,"Ypos":0.5,"isVisitedPoint":false,"isPossibleToMove":false,"isExplorerOnMe":false,"canGoUp":true,"canGoDown":false,"canGoRight":false,"canGoLeft":true,"levelOfPoint":0},{"Xpos":-0.5,"Ypos":0.5,"isVisitedPoint":false,"isPossibleToMove":false,"isExplorerOnMe":false,"canGoUp":false,"canGoDown":false,"canGoRight":true,"canGoLeft":false,"levelOfPoint":0},{"Xpos":0.5,"Ypos":-0.5,"isVisitedPoint":false,"isPossibleToMove":false,"isExplorerOnMe":false,"canGoUp":true,"canGoDown":false,"canGoRight":false,"canGoLeft":true,"levelOfPoint":0},{"Xpos":-0.5,"Ypos":-0.5,"isVisitedPoint":false,"isPossibleToMove":false,"isExplorerOnMe":false,"canGoUp":false,"canGoDown":false,"canGoRight":true,"canGoLeft":false,"levelOfPoint":0},{"Xpos":4.5,"Ypos":2.5,"isVisitedPoint":false,"isPossibleToMove":false,"isExplorerOnMe":false,"canGoUp":false,"canGoDown":false,"canGoRight":false,"canGoLeft":true,"levelOfPoint":0},{"Xpos":3.5,"Ypos":2.5,"isVisitedPoint":false,"isPossibleToMove":false,"isExplorerOnMe":false,"canGoUp":false,"canGoDown":false,"canGoRight":true,"canGoLeft":true,"levelOfPoint":0},{"Xpos":3.5,"Ypos":1.5,"isVisitedPoint":false,"isPossibleToMove":false,"isExplorerOnMe":false,"canGoUp":false,"canGoDown":true,"canGoRight":false,"canGoLeft":false,"levelOfPoint":0},{"Xpos":2.5,"Ypos":2.5,"isVisitedPoint":false,"isPossibleToMove":false,"isExplorerOnMe":false,"canGoUp":false,"canGoDown":true,"canGoRight":true,"canGoLeft":true,"levelOfPoint":0},{"Xpos":1.5,"Ypos":2.5,"isVisitedPoint":false,"isPossibleToMove":false,"isExplorerOnMe":false,"canGoUp":false,"canGoDown":false,"canGoRight":true,"canGoLeft":true,"levelOfPoint":0},{"Xpos":2.5,"Ypos":1.5,"isVisitedPoint":false,"isPossibleToMove":false,"isExplorerOnMe":false,"canGoUp":true,"canGoDown":false,"canGoRight":false,"canGoLeft":false,"levelOfPoint":0},{"Xpos":1.5,"Ypos":1.5,"isVisitedPoint":false,"isPossibleToMove":false,"isExplorerOnMe":false,"canGoUp":false,"canGoDown":true,"canGoRight":false,"canGoLeft":false,"levelOfPoint":0},{"Xpos":0.5,"Ypos":2.5,"isVisitedPoint":false,"isPossibleToMove":false,"isExplorerOnMe":false,"canGoUp":false,"canGoDown":true,"canGoRight":true,"canGoLeft":true,"levelOfPoint":0},{"Xpos":-0.5,"Ypos":2.5,"isVisitedPoint":false,"isPossibleToMove":false,"isExplorerOnMe":false,"canGoUp":false,"canGoDown":true,"canGoRight":true,"canGoLeft":false,"levelOfPoint":0},{"Xpos":0.5,"Ypos":1.5,"isVisitedPoint":false,"isPossibleToMove":false,"isExplorerOnMe":false,"canGoUp":true,"canGoDown":true,"canGoRight":false,"canGoLeft":false,"levelOfPoint":0},{"Xpos":-0.5,"Ypos":1.5,"isVisitedPoint":false,"isPossibleToMove":false,"isExplorerOnMe":false,"canGoUp":true,"canGoDown":false,"canGoRight":false,"canGoLeft":false,"levelOfPoint":0},{"Xpos":3.5,"Ypos":0.5,"isVisitedPoint":false,"isPossibleToMove":false,"isExplorerOnMe":false,"canGoUp":true,"canGoDown":true,"canGoRight":false,"canGoLeft":false,"levelOfPoint":0},{"Xpos":4.5,"Ypos":-0.5,"isVisitedPoint":false,"isPossibleToMove":false,"isExplorerOnMe":false,"canGoUp":false,"canGoDown":false,"canGoRight":false,"canGoLeft":true,"levelOfPoint":0},{"Xpos":3.5,"Ypos":-0.5,"isVisitedPoint":false,"isPossibleToMove":false,"isExplorerOnMe":false,"canGoUp":true,"canGoDown":false,"canGoRight":true,"canGoLeft":true,"levelOfPoint":0},{"Xpos":2.5,"Ypos":0.5,"isVisitedPoint":false,"isPossibleToMove":false,"isExplorerOnMe":false,"canGoUp":false,"canGoDown":true,"canGoRight":false,"canGoLeft":false,"levelOfPoint":0},{"Xpos":1.5,"Ypos":0.5,"isVisitedPoint":false,"isPossibleToMove":false,"isExplorerOnMe":false,"canGoUp":true,"canGoDown":true,"canGoRight":false,"canGoLeft":false,"levelOfPoint":0},{"Xpos":2.5,"Ypos":-0.5,"isVisitedPoint":false,"isPossibleToMove":false,"isExplorerOnMe":false,"canGoUp":true,"canGoDown":false,"canGoRight":true,"canGoLeft":true,"levelOfPoint":0},{"Xpos":1.5,"Ypos":-0.5,"isVisitedPoint":false,"isPossibleToMove":false,"isExplorerOnMe":false,"canGoUp":true,"canGoDown":false,"canGoRight":true,"canGoLeft":true,"levelOfPoint":0},{"Xpos":0.5,"Ypos":0.5,"isVisitedPoint":false,"isPossibleToMove":false,"isExplorerOnMe":false,"canGoUp":true,"canGoDown":true,"canGoRight":false,"canGoLeft":true,"levelOfPoint":0},{"Xpos":-0.5,"Ypos":0.5,"isVisitedPoint":false,"isPossibleToMove":false,"isExplorerOnMe":false,"canGoUp":false,"canGoDown":false,"canGoRight":true,"canGoLeft":false,"levelOfPoint":0},{"Xpos":0.5,"Ypos":-0.5,"isVisitedPoint":false,"isPossibleToMove":false,"isExplorerOnMe":false,"canGoUp":true,"canGoDown":false,"canGoRight":true,"canGoLeft":true,"levelOfPoint":0},{"Xpos":-0.5,"Ypos":-0.5,"isVisitedPoint":false,"isPossibleToMove":false,"isExplorerOnMe":false,"canGoUp":false,"canGoDown":false,"canGoRight":true,"canGoLeft":false,"levelOfPoint":0},{"Xpos":-1.2100000381469727,"Ypos":-2.25,"isVisitedPoint":false,"isPossibleToMove":false,"isExplorerOnMe":false,"canGoUp":true,"canGoDown":true,"canGoRight":false,"canGoLeft":false,"levelOfPoint":0},{"Xpos":-0.20999997854232789,"Ypos":-3.25,"isVisitedPoint":false,"isPossibleToMove":false,"isExplorerOnMe":false,"canGoUp":false,"canGoDown":false,"canGoRight":false,"canGoLeft":true,"levelOfPoint":0},{"Xpos":-1.2100000381469727,"Ypos":-3.25,"isVisitedPoint":false,"isPossibleToMove":false,"isExplorerOnMe":false,"canGoUp":true,"canGoDown":false,"canGoRight":true,"canGoLeft":true,"levelOfPoint":0},{"Xpos":-3.0799999237060549,"Ypos":0.8899999856948853,"isVisitedPoint":false,"isPossibleToMove":false,"isExplorerOnMe":false,"canGoUp":false,"canGoDown":false,"canGoRight":true,"canGoLeft":true,"levelOfPoint":0},{"Xpos":-4.079999923706055,"Ypos":0.8899999856948853,"isVisitedPoint":false,"isPossibleToMove":false,"isExplorerOnMe":false,"canGoUp":false,"canGoDown":true,"canGoRight":true,"canGoLeft":true,"levelOfPoint":0},{"Xpos":-4.079999923706055,"Ypos":-0.11000001430511475,"isVisitedPoint":false,"isPossibleToMove":false,"isExplorerOnMe":false,"canGoUp":true,"canGoDown":true,"canGoRight":false,"canGoLeft":false,"levelOfPoint":0},{"Xpos":-3.0999999046325685,"Ypos":-2.2699999809265138,"isVisitedPoint":false,"isPossibleToMove":false,"isExplorerOnMe":false,"canGoUp":false,"canGoDown":true,"canGoRight":false,"canGoLeft":true,"levelOfPoint":0},{"Xpos":-4.099999904632568,"Ypos":-2.2699999809265138,"isVisitedPoint":false,"isPossibleToMove":false,"isExplorerOnMe":false,"canGoUp":true,"canGoDown":true,"canGoRight":true,"canGoLeft":false,"levelOfPoint":0},{"Xpos":-3.0999999046325685,"Ypos":-3.2699999809265138,"isVisitedPoint":false,"isPossibleToMove":false,"isExplorerOnMe":false,"canGoUp":true,"canGoDown":false,"canGoRight":true,"canGoLeft":false,"levelOfPoint":0},{"Xpos":-4.099999904632568,"Ypos":-3.2699999809265138,"isVisitedPoint":false,"isPossibleToMove":false,"isExplorerOnMe":false,"canGoUp":true,"canGoDown":false,"canGoRight":false,"canGoLeft":true,"levelOfPoint":0},{"Xpos":-5.929999828338623,"Ypos":-2.190000057220459,"isVisitedPoint":false,"isPossibleToMove":false,"isExplorerOnMe":false,"canGoUp":true,"canGoDown":true,"canGoRight":false,"canGoLeft":false,"levelOfPoint":0},{"Xpos":-5.929999828338623,"Ypos":-3.190000057220459,"isVisitedPoint":false,"isPossibleToMove":false,"isExplorerOnMe":false,"canGoUp":true,"canGoDown":false,"canGoRight":true,"canGoLeft":true,"levelOfPoint":0},{"Xpos":-6.929999828338623,"Ypos":-3.190000057220459,"isVisitedPoint":false,"isPossibleToMove":false,"isExplorerOnMe":false,"canGoUp":false,"canGoDown":false,"canGoRight":true,"canGoLeft":false,"levelOfPoint":0},{"Xpos":-0.1499999761581421,"Ypos":0.9099999666213989,"isVisitedPoint":false,"isPossibleToMove":false,"isExplorerOnMe":false,"canGoUp":false,"canGoDown":true,"canGoRight":false,"canGoLeft":false,"levelOfPoint":0},{"Xpos":-1.149999976158142,"Ypos":0.9099999666213989,"isVisitedPoint":false,"isPossibleToMove":false,"isExplorerOnMe":false,"canGoUp":false,"canGoDown":false,"canGoRight":false,"canGoLeft":true,"levelOfPoint":0},{"Xpos":-0.1499999761581421,"Ypos":-0.09000000357627869,"isVisitedPoint":false,"isPossibleToMove":false,"isExplorerOnMe":false,"canGoUp":true,"canGoDown":false,"canGoRight":false,"canGoLeft":true,"levelOfPoint":0},{"Xpos":-1.149999976158142,"Ypos":-0.09000000357627869,"isVisitedPoint":false,"isPossibleToMove":false,"isExplorerOnMe":false,"canGoUp":false,"canGoDown":true,"canGoRight":true,"canGoLeft":false,"levelOfPoint":0},{"Xpos":-5.900000095367432,"Ypos":0.949999988079071,"isVisitedPoint":false,"isPossibleToMove":false,"isExplorerOnMe":false,"canGoUp":true,"canGoDown":true,"canGoRight":false,"canGoLeft":false,"levelOfPoint":0},{"Xpos":-5.900000095367432,"Ypos":-0.050000011920928958,"isVisitedPoint":false,"isPossibleToMove":false,"isExplorerOnMe":false,"canGoUp":true,"canGoDown":false,"canGoRight":true,"canGoLeft":true,"levelOfPoint":0},{"Xpos":-6.900000095367432,"Ypos":-0.050000011920928958,"isVisitedPoint":false,"isPossibleToMove":false,"isExplorerOnMe":false,"canGoUp":false,"canGoDown":false,"canGoRight":true,"canGoLeft":false,"levelOfPoint":0},{"Xpos":4.5,"Ypos":2.5,"isVisitedPoint":false,"isPossibleToMove":false,"isExplorerOnMe":false,"canGoUp":false,"canGoDown":false,"canGoRight":false,"canGoLeft":true,"levelOfPoint":0},{"Xpos":3.5,"Ypos":2.5,"isVisitedPoint":false,"isPossibleToMove":false,"isExplorerOnMe":false,"canGoUp":false,"canGoDown":false,"canGoRight":true,"canGoLeft":true,"levelOfPoint":0},{"Xpos":3.5,"Ypos":1.5,"isVisitedPoint":false,"isPossibleToMove":false,"isExplorerOnMe":false,"canGoUp":false,"canGoDown":true,"canGoRight":false,"canGoLeft":false,"levelOfPoint":0},{"Xpos":2.5,"Ypos":2.5,"isVisitedPoint":false,"isPossibleToMove":false,"isExplorerOnMe":false,"canGoUp":false,"canGoDown":true,"canGoRight":true,"canGoLeft":true,"levelOfPoint":0},{"Xpos":1.5,"Ypos":2.5,"isVisitedPoint":false,"isPossibleToMove":false,"isExplorerOnMe":false,"canGoUp":false,"canGoDown":false,"canGoRight":true,"canGoLeft":true,"levelOfPoint":0},{"Xpos":2.5,"Ypos":1.5,"isVisitedPoint":false,"isPossibleToMove":false,"isExplorerOnMe":false,"canGoUp":true,"canGoDown":false,"canGoRight":false,"canGoLeft":false,"levelOfPoint":0},{"Xpos":1.5,"Ypos":1.5,"isVisitedPoint":false,"isPossibleToMove":false,"isExplorerOnMe":false,"canGoUp":false,"canGoDown":true,"canGoRight":false,"canGoLeft":false,"levelOfPoint":0},{"Xpos":0.5,"Ypos":2.5,"isVisitedPoint":false,"isPossibleToMove":false,"isExplorerOnMe":false,"canGoUp":false,"canGoDown":true,"canGoRight":true,"canGoLeft":true,"levelOfPoint":0},{"Xpos":-0.5,"Ypos":2.5,"isVisitedPoint":false,"isPossibleToMove":false,"isExplorerOnMe":false,"canGoUp":false,"canGoDown":true,"canGoRight":true,"canGoLeft":false,"levelOfPoint":0},{"Xpos":0.5,"Ypos":1.5,"isVisitedPoint":false,"isPossibleToMove":false,"isExplorerOnMe":false,"canGoUp":true,"canGoDown":true,"canGoRight":false,"canGoLeft":false,"levelOfPoint":0},{"Xpos":-0.5,"Ypos":1.5,"isVisitedPoint":false,"isPossibleToMove":false,"isExplorerOnMe":false,"canGoUp":true,"canGoDown":false,"canGoRight":false,"canGoLeft":false,"levelOfPoint":0},{"Xpos":3.5,"Ypos":0.5,"isVisitedPoint":false,"isPossibleToMove":false,"isExplorerOnMe":false,"canGoUp":true,"canGoDown":true,"canGoRight":false,"canGoLeft":false,"levelOfPoint":0},{"Xpos":4.5,"Ypos":-0.5,"isVisitedPoint":false,"isPossibleToMove":false,"isExplorerOnMe":false,"canGoUp":false,"canGoDown":false,"canGoRight":false,"canGoLeft":true,"levelOfPoint":0},{"Xpos":3.5,"Ypos":-0.5,"isVisitedPoint":false,"isPossibleToMove":false,"isExplorerOnMe":false,"canGoUp":true,"canGoDown":false,"canGoRight":true,"canGoLeft":true,"levelOfPoint":0},{"Xpos":2.5,"Ypos":0.5,"isVisitedPoint":false,"isPossibleToMove":false,"isExplorerOnMe":false,"canGoUp":false,"canGoDown":true,"canGoRight":false,"canGoLeft":false,"levelOfPoint":0},{"Xpos":1.5,"Ypos":0.5,"isVisitedPoint":false,"isPossibleToMove":false,"isExplorerOnMe":false,"canGoUp":true,"canGoDown":true,"canGoRight":false,"canGoLeft":false,"levelOfPoint":0},{"Xpos":2.5,"Ypos":-0.5,"isVisitedPoint":false,"isPossibleToMove":false,"isExplorerOnMe":false,"canGoUp":true,"canGoDown":false,"canGoRight":true,"canGoLeft":true,"levelOfPoint":0},{"Xpos":1.5,"Ypos":-0.5,"isVisitedPoint":false,"isPossibleToMove":false,"isExplorerOnMe":false,"canGoUp":true,"canGoDown":false,"canGoRight":true,"canGoLeft":true,"levelOfPoint":0},{"Xpos":0.5,"Ypos":0.5,"isVisitedPoint":false,"isPossibleToMove":false,"isExplorerOnMe":false,"canGoUp":true,"canGoDown":true,"canGoRight":false,"canGoLeft":true,"levelOfPoint":0},{"Xpos":-0.5,"Ypos":0.5,"isVisitedPoint":false,"isPossibleToMove":false,"isExplorerOnMe":false,"canGoUp":false,"canGoDown":false,"canGoRight":true,"canGoLeft":false,"levelOfPoint":0},{"Xpos":0.5,"Ypos":-0.5,"isVisitedPoint":false,"isPossibleToMove":false,"isExplorerOnMe":false,"canGoUp":true,"canGoDown":false,"canGoRight":true,"canGoLeft":true,"levelOfPoint":0},{"Xpos":-0.5,"Ypos":-0.5,"isVisitedPoint":false,"isPossibleToMove":false,"isExplorerOnMe":false,"canGoUp":false,"canGoDown":false,"canGoRight":true,"canGoLeft":false,"levelOfPoint":0},{"Xpos":4.5,"Ypos":2.5,"isVisitedPoint":false,"isPossibleToMove":false,"isExplorerOnMe":false,"canGoUp":false,"canGoDown":false,"canGoRight":false,"canGoLeft":true,"levelOfPoint":0},{"Xpos":3.5,"Ypos":2.5,"isVisitedPoint":false,"isPossibleToMove":false,"isExplorerOnMe":false,"canGoUp":false,"canGoDown":false,"canGoRight":true,"canGoLeft":true,"levelOfPoint":0},{"Xpos":3.5,"Ypos":1.5,"isVisitedPoint":false,"isPossibleToMove":false,"isExplorerOnMe":false,"canGoUp":false,"canGoDown":true,"canGoRight":false,"canGoLeft":false,"levelOfPoint":0},{"Xpos":2.5,"Ypos":2.5,"isVisitedPoint":false,"isPossibleToMove":false,"isExplorerOnMe":false,"canGoUp":false,"canGoDown":true,"canGoRight":true,"canGoLeft":true,"levelOfPoint":0},{"Xpos":1.5,"Ypos":2.5,"isVisitedPoint":false,"isPossibleToMove":false,"isExplorerOnMe":false,"canGoUp":false,"canGoDown":false,"canGoRight":true,"canGoLeft":true,"levelOfPoint":0},{"Xpos":2.5,"Ypos":1.5,"isVisitedPoint":false,"isPossibleToMove":false,"isExplorerOnMe":false,"canGoUp":true,"canGoDown":false,"canGoRight":false,"canGoLeft":false,"levelOfPoint":0},{"Xpos":1.5,"Ypos":1.5,"isVisitedPoint":false,"isPossibleToMove":false,"isExplorerOnMe":false,"canGoUp":false,"canGoDown":true,"canGoRight":false,"canGoLeft":false,"levelOfPoint":0},{"Xpos":0.5,"Ypos":2.5,"isVisitedPoint":false,"isPossibleToMove":false,"isExplorerOnMe":false,"canGoUp":false,"canGoDown":true,"canGoRight":true,"canGoLeft":true,"levelOfPoint":0},{"Xpos":-0.5,"Ypos":2.5,"isVisitedPoint":false,"isPossibleToMove":false,"isExplorerOnMe":false,"canGoUp":false,"canGoDown":true,"canGoRight":true,"canGoLeft":false,"levelOfPoint":0},{"Xpos":0.5,"Ypos":1.5,"isVisitedPoint":false,"isPossibleToMove":false,"isExplorerOnMe":false,"canGoUp":true,"canGoDown":true,"canGoRight":false,"canGoLeft":false,"levelOfPoint":0},{"Xpos":-0.5,"Ypos":1.5,"isVisitedPoint":false,"isPossibleToMove":false,"isExplorerOnMe":false,"canGoUp":true,"canGoDown":false,"canGoRight":false,"canGoLeft":false,"levelOfPoint":0},{"Xpos":3.5,"Ypos":0.5,"isVisitedPoint":false,"isPossibleToMove":false,"isExplorerOnMe":false,"canGoUp":true,"canGoDown":true,"canGoRight":false,"canGoLeft":false,"levelOfPoint":0},{"Xpos":4.5,"Ypos":-0.5,"isVisitedPoint":false,"isPossibleToMove":false,"isExplorerOnMe":false,"canGoUp":false,"canGoDown":false,"canGoRight":false,"canGoLeft":true,"levelOfPoint":0},{"Xpos":3.5,"Ypos":-0.5,"isVisitedPoint":false,"isPossibleToMove":false,"isExplorerOnMe":false,"canGoUp":true,"canGoDown":false,"canGoRight":true,"canGoLeft":true,"levelOfPoint":0},{"Xpos":2.5,"Ypos":0.5,"isVisitedPoint":false,"isPossibleToMove":false,"isExplorerOnMe":false,"canGoUp":false,"canGoDown":true,"canGoRight":false,"canGoLeft":false,"levelOfPoint":0},{"Xpos":1.5,"Ypos":0.5,"isVisitedPoint":false,"isPossibleToMove":false,"isExplorerOnMe":false,"canGoUp":true,"canGoDown":true,"canGoRight":false,"canGoLeft":false,"levelOfPoint":0},{"Xpos":2.5,"Ypos":-0.5,"isVisitedPoint":false,"isPossibleToMove":false,"isExplorerOnMe":false,"canGoUp":true,"canGoDown":false,"canGoRight":true,"canGoLeft":true,"levelOfPoint":0},{"Xpos":1.5,"Ypos":-0.5,"isVisitedPoint":false,"isPossibleToMove":false,"isExplorerOnMe":false,"canGoUp":true,"canGoDown":false,"canGoRight":true,"canGoLeft":true,"levelOfPoint":0},{"Xpos":0.5,"Ypos":0.5,"isVisitedPoint":false,"isPossibleToMove":false,"isExplorerOnMe":false,"canGoUp":true,"canGoDown":true,"canGoRight":false,"canGoLeft":true,"levelOfPoint":0},{"Xpos":-0.5,"Ypos":0.5,"isVisitedPoint":false,"isPossibleToMove":false,"isExplorerOnMe":false,"canGoUp":false,"canGoDown":false,"canGoRight":true,"canGoLeft":false,"levelOfPoint":0},{"Xpos":0.5,"Ypos":-0.5,"isVisitedPoint":false,"isPossibleToMove":false,"isExplorerOnMe":false,"canGoUp":true,"canGoDown":false,"canGoRight":true,"canGoLeft":true,"levelOfPoint":0},{"Xpos":-0.5,"Ypos":-0.5,"isVisitedPoint":false,"isPossibleToMove":false,"isExplorerOnMe":false,"canGoUp":false,"canGoDown":false,"canGoRight":true,"canGoLeft":false,"levelOfPoint":0},{"Xpos":4.5,"Ypos":2.5,"isVisitedPoint":false,"isPossibleToMove":false,"isExplorerOnMe":false,"canGoUp":false,"canGoDown":false,"canGoRight":false,"canGoLeft":true,"levelOfPoint":0},{"Xpos":3.5,"Ypos":2.5,"isVisitedPoint":false,"isPossibleToMove":false,"isExplorerOnMe":false,"canGoUp":false,"canGoDown":false,"canGoRight":true,"canGoLeft":true,"levelOfPoint":0},{"Xpos":3.5,"Ypos":1.5,"isVisitedPoint":false,"isPossibleToMove":false,"isExplorerOnMe":false,"canGoUp":false,"canGoDown":true,"canGoRight":false,"canGoLeft":false,"levelOfPoint":0},{"Xpos":2.5,"Ypos":2.5,"isVisitedPoint":false,"isPossibleToMove":false,"isExplorerOnMe":false,"canGoUp":false,"canGoDown":true,"canGoRight":true,"canGoLeft":true,"levelOfPoint":0},{"Xpos":1.5,"Ypos":2.5,"isVisitedPoint":false,"isPossibleToMove":false,"isExplorerOnMe":false,"canGoUp":false,"canGoDown":false,"canGoRight":true,"canGoLeft":true,"levelOfPoint":0},{"Xpos":2.5,"Ypos":1.5,"isVisitedPoint":false,"isPossibleToMove":false,"isExplorerOnMe":false,"canGoUp":true,"canGoDown":false,"canGoRight":false,"canGoLeft":false,"levelOfPoint":0},{"Xpos":1.5,"Ypos":1.5,"isVisitedPoint":false,"isPossibleToMove":false,"isExplorerOnMe":false,"canGoUp":false,"canGoDown":true,"canGoRight":false,"canGoLeft":false,"levelOfPoint":0},{"Xpos":0.5,"Ypos":2.5,"isVisitedPoint":false,"isPossibleToMove":false,"isExplorerOnMe":false,"canGoUp":false,"canGoDown":true,"canGoRight":true,"canGoLeft":true,"levelOfPoint":0},{"Xpos":-0.5,"Ypos":2.5,"isVisitedPoint":false,"isPossibleToMove":false,"isExplorerOnMe":false,"canGoUp":false,"canGoDown":true,"canGoRight":true,"canGoLeft":false,"levelOfPoint":0},{"Xpos":0.5,"Ypos":1.5,"isVisitedPoint":false,"isPossibleToMove":false,"isExplorerOnMe":false,"canGoUp":true,"canGoDown":true,"canGoRight":false,"canGoLeft":false,"levelOfPoint":0},{"Xpos":-0.5,"Ypos":1.5,"isVisitedPoint":false,"isPossibleToMove":false,"isExplorerOnMe":false,"canGoUp":true,"canGoDown":false,"canGoRight":false,"canGoLeft":false,"levelOfPoint":0},{"Xpos":3.5,"Ypos":0.5,"isVisitedPoint":false,"isPossibleToMove":false,"isExplorerOnMe":false,"canGoUp":true,"canGoDown":true,"canGoRight":false,"canGoLeft":false,"levelOfPoint":0},{"Xpos":4.5,"Ypos":-0.5,"isVisitedPoint":false,"isPossibleToMove":false,"isExplorerOnMe":false,"canGoUp":false,"canGoDown":false,"canGoRight":false,"canGoLeft":true,"levelOfPoint":0},{"Xpos":3.5,"Ypos":-0.5,"isVisitedPoint":false,"isPossibleToMove":false,"isExplorerOnMe":false,"canGoUp":true,"canGoDown":false,"canGoRight":true,"canGoLeft":true,"levelOfPoint":0},{"Xpos":2.5,"Ypos":0.5,"isVisitedPoint":false,"isPossibleToMove":false,"isExplorerOnMe":false,"canGoUp":false,"canGoDown":true,"canGoRight":false,"canGoLeft":false,"levelOfPoint":0},{"Xpos":1.5,"Ypos":0.5,"isVisitedPoint":false,"isPossibleToMove":false,"isExplorerOnMe":false,"canGoUp":true,"canGoDown":true,"canGoRight":false,"canGoLeft":false,"levelOfPoint":0},{"Xpos":2.5,"Ypos":-0.5,"isVisitedPoint":false,"isPossibleToMove":false,"isExplorerOnMe":false,"canGoUp":true,"canGoDown":false,"canGoRight":true,"canGoLeft":true,"levelOfPoint":0},{"Xpos":1.5,"Ypos":-0.5,"isVisitedPoint":false,"isPossibleToMove":false,"isExplorerOnMe":false,"canGoUp":true,"canGoDown":false,"canGoRight":true,"canGoLeft":true,"levelOfPoint":0},{"Xpos":0.5,"Ypos":0.5,"isVisitedPoint":false,"isPossibleToMove":false,"isExplorerOnMe":false,"canGoUp":true,"canGoDown":true,"canGoRight":false,"canGoLeft":true,"levelOfPoint":0},{"Xpos":-0.5,"Ypos":0.5,"isVisitedPoint":false,"isPossibleToMove":false,"isExplorerOnMe":false,"canGoUp":false,"canGoDown":false,"canGoRight":true,"canGoLeft":false,"levelOfPoint":0},{"Xpos":0.5,"Ypos":-0.5,"isVisitedPoint":false,"isPossibleToMove":false,"isExplorerOnMe":false,"canGoUp":true,"canGoDown":false,"canGoRight":true,"canGoLeft":true,"levelOfPoint":0},{"Xpos":-0.5,"Ypos":-0.5,"isVisitedPoint":false,"isPossibleToMove":false,"isExplorerOnMe":false,"canGoUp":false,"canGoDown":false,"canGoRight":true,"canGoLeft":false,"levelOfPoint":0},{"Xpos":4.5,"Ypos":2.5,"isVisitedPoint":false,"isPossibleToMove":false,"isExplorerOnMe":false,"canGoUp":false,"canGoDown":false,"canGoRight":false,"canGoLeft":true,"levelOfPoint":0},{"Xpos":3.5,"Ypos":2.5,"isVisitedPoint":false,"isPossibleToMove":false,"isExplorerOnMe":false,"canGoUp":false,"canGoDown":false,"canGoRight":true,"canGoLeft":true,"levelOfPoint":0},{"Xpos":3.5,"Ypos":1.5,"isVisitedPoint":false,"isPossibleToMove":false,"isExplorerOnMe":false,"canGoUp":false,"canGoDown":true,"canGoRight":false,"canGoLeft":false,"levelOfPoint":0},{"Xpos":2.5,"Ypos":2.5,"isVisitedPoint":false,"isPossibleToMove":false,"isExplorerOnMe":false,"canGoUp":false,"canGoDown":true,"canGoRight":true,"canGoLeft":true,"levelOfPoint":0},{"Xpos":1.5,"Ypos":2.5,"isVisitedPoint":false,"isPossibleToMove":false,"isExplorerOnMe":false,"canGoUp":false,"canGoDown":false,"canGoRight":true,"canGoLeft":true,"levelOfPoint":0},{"Xpos":2.5,"Ypos":1.5,"isVisitedPoint":false,"isPossibleToMove":false,"isExplorerOnMe":false,"canGoUp":true,"canGoDown":false,"canGoRight":false,"canGoLeft":false,"levelOfPoint":0},{"Xpos":1.5,"Ypos":1.5,"isVisitedPoint":false,"isPossibleToMove":false,"isExplorerOnMe":false,"canGoUp":false,"canGoDown":true,"canGoRight":false,"canGoLeft":false,"levelOfPoint":0},{"Xpos":0.5,"Ypos":2.5,"isVisitedPoint":false,"isPossibleToMove":false,"isExplorerOnMe":false,"canGoUp":false,"canGoDown":true,"canGoRight":true,"canGoLeft":true,"levelOfPoint":0},{"Xpos":-0.5,"Ypos":2.5,"isVisitedPoint":false,"isPossibleToMove":false,"isExplorerOnMe":false,"canGoUp":false,"canGoDown":true,"canGoRight":true,"canGoLeft":false,"levelOfPoint":0},{"Xpos":0.5,"Ypos":1.5,"isVisitedPoint":false,"isPossibleToMove":false,"isExplorerOnMe":false,"canGoUp":true,"canGoDown":true,"canGoRight":false,"canGoLeft":false,"levelOfPoint":0},{"Xpos":-0.5,"Ypos":1.5,"isVisitedPoint":false,"isPossibleToMove":false,"isExplorerOnMe":false,"canGoUp":true,"canGoDown":false,"canGoRight":false,"canGoLeft":false,"levelOfPoint":0},{"Xpos":3.5,"Ypos":0.5,"isVisitedPoint":false,"isPossibleToMove":false,"isExplorerOnMe":false,"canGoUp":true,"canGoDown":true,"canGoRight":false,"canGoLeft":false,"levelOfPoint":0},{"Xpos":4.5,"Ypos":-0.5,"isVisitedPoint":false,"isPossibleToMove":false,"isExplorerOnMe":false,"canGoUp":false,"canGoDown":false,"canGoRight":false,"canGoLeft":true,"levelOfPoint":0},{"Xpos":3.5,"Ypos":-0.5,"isVisitedPoint":false,"isPossibleToMove":false,"isExplorerOnMe":false,"canGoUp":true,"canGoDown":false,"canGoRight":true,"canGoLeft":true,"levelOfPoint":0},{"Xpos":2.5,"Ypos":0.5,"isVisitedPoint":false,"isPossibleToMove":false,"isExplorerOnMe":false,"canGoUp":false,"canGoDown":true,"canGoRight":false,"canGoLeft":false,"levelOfPoint":0},{"Xpos":1.5,"Ypos":0.5,"isVisitedPoint":false,"isPossibleToMove":false,"isExplorerOnMe":false,"canGoUp":true,"canGoDown":true,"canGoRight":false,"canGoLeft":false,"levelOfPoint":0},{"Xpos":2.5,"Ypos":-0.5,"isVisitedPoint":false,"isPossibleToMove":false,"isExplorerOnMe":false,"canGoUp":true,"canGoDown":false,"canGoRight":true,"canGoLeft":true,"levelOfPoint":0},{"Xpos":1.5,"Ypos":-0.5,"isVisitedPoint":false,"isPossibleToMove":false,"isExplorerOnMe":false,"canGoUp":true,"canGoDown":false,"canGoRight":true,"canGoLeft":true,"levelOfPoint":0},{"Xpos":0.5,"Ypos":0.5,"isVisitedPoint":false,"isPossibleToMove":false,"isExplorerOnMe":false,"canGoUp":true,"canGoDown":true,"canGoRight":false,"canGoLeft":true,"levelOfPoint":0},{"Xpos":-0.5,"Ypos":0.5,"isVisitedPoint":false,"isPossibleToMove":false,"isExplorerOnMe":false,"canGoUp":false,"canGoDown":false,"canGoRight":true,"canGoLeft":false,"levelOfPoint":0},{"Xpos":0.5,"Ypos":-0.5,"isVisitedPoint":false,"isPossibleToMove":false,"isExplorerOnMe":false,"canGoUp":true,"canGoDown":false,"canGoRight":true,"canGoLeft":true,"levelOfPoint":0},{"Xpos":-0.5,"Ypos":-0.5,"isVisitedPoint":false,"isPossibleToMove":false,"isExplorerOnMe":false,"canGoUp":false,"canGoDown":false,"canGoRight":true,"canGoLeft":false,"levelOfPoint":0},{"Xpos":4.5,"Ypos":2.5,"isVisitedPoint":false,"isPossibleToMove":false,"isExplorerOnMe":false,"canGoUp":false,"canGoDown":false,"canGoRight":false,"canGoLeft":true,"levelOfPoint":0},{"Xpos":3.5,"Ypos":2.5,"isVisitedPoint":false,"isPossibleToMove":false,"isExplorerOnMe":false,"canGoUp":false,"canGoDown":false,"canGoRight":true,"canGoLeft":true,"levelOfPoint":0},{"Xpos":3.5,"Ypos":1.5,"isVisitedPoint":false,"isPossibleToMove":false,"isExplorerOnMe":false,"canGoUp":false,"canGoDown":true,"canGoRight":false,"canGoLeft":false,"levelOfPoint":0},{"Xpos":2.5,"Ypos":2.5,"isVisitedPoint":false,"isPossibleToMove":false,"isExplorerOnMe":false,"canGoUp":false,"canGoDown":true,"canGoRight":true,"canGoLeft":true,"levelOfPoint":0},{"Xpos":1.5,"Ypos":2.5,"isVisitedPoint":false,"isPossibleToMove":false,"isExplorerOnMe":false,"canGoUp":false,"canGoDown":false,"canGoRight":true,"canGoLeft":true,"levelOfPoint":0},{"Xpos":2.5,"Ypos":1.5,"isVisitedPoint":false,"isPossibleToMove":false,"isExplorerOnMe":false,"canGoUp":true,"canGoDown":false,"canGoRight":false,"canGoLeft":false,"levelOfPoint":0},{"Xpos":1.5,"Ypos":1.5,"isVisitedPoint":false,"isPossibleToMove":false,"isExplorerOnMe":false,"canGoUp":false,"canGoDown":true,"canGoRight":false,"canGoLeft":false,"levelOfPoint":0},{"Xpos":0.5,"Ypos":2.5,"isVisitedPoint":false,"isPossibleToMove":false,"isExplorerOnMe":false,"canGoUp":false,"canGoDown":true,"canGoRight":true,"canGoLeft":true,"levelOfPoint":0},{"Xpos":-0.5,"Ypos":2.5,"isVisitedPoint":false,"isPossibleToMove":false,"isExplorerOnMe":false,"canGoUp":false,"canGoDown":true,"canGoRight":true,"canGoLeft":false,"levelOfPoint":0},{"Xpos":0.5,"Ypos":1.5,"isVisitedPoint":false,"isPossibleToMove":false,"isExplorerOnMe":false,"canGoUp":true,"canGoDown":true,"canGoRight":false,"canGoLeft":false,"levelOfPoint":0},{"Xpos":-0.5,"Ypos":1.5,"isVisitedPoint":false,"isPossibleToMove":false,"isExplorerOnMe":false,"canGoUp":true,"canGoDown":false,"canGoRight":false,"canGoLeft":false,"levelOfPoint":0},{"Xpos":3.5,"Ypos":0.5,"isVisitedPoint":false,"isPossibleToMove":false,"isExplorerOnMe":false,"canGoUp":true,"canGoDown":true,"canGoRight":false,"canGoLeft":false,"levelOfPoint":0},{"Xpos":4.5,"Ypos":-0.5,"isVisitedPoint":false,"isPossibleToMove":false,"isExplorerOnMe":false,"canGoUp":false,"canGoDown":false,"canGoRight":false,"canGoLeft":true,"levelOfPoint":0},{"Xpos":3.5,"Ypos":-0.5,"isVisitedPoint":false,"isPossibleToMove":false,"isExplorerOnMe":false,"canGoUp":true,"canGoDown":false,"canGoRight":true,"canGoLeft":true,"levelOfPoint":0},{"Xpos":2.5,"Ypos":0.5,"isVisitedPoint":false,"isPossibleToMove":false,"isExplorerOnMe":false,"canGoUp":false,"canGoDown":true,"canGoRight":false,"canGoLeft":false,"levelOfPoint":0},{"Xpos":1.5,"Ypos":0.5,"isVisitedPoint":false,"isPossibleToMove":false,"isExplorerOnMe":false,"canGoUp":true,"canGoDown":true,"canGoRight":false,"canGoLeft":false,"levelOfPoint":0},{"Xpos":2.5,"Ypos":-0.5,"isVisitedPoint":false,"isPossibleToMove":false,"isExplorerOnMe":false,"canGoUp":true,"canGoDown":false,"canGoRight":true,"canGoLeft":true,"levelOfPoint":0},{"Xpos":1.5,"Ypos":-0.5,"isVisitedPoint":false,"isPossibleToMove":false,"isExplorerOnMe":false,"canGoUp":true,"canGoDown":false,"canGoRight":true,"canGoLeft":true,"levelOfPoint":0},{"Xpos":0.5,"Ypos":0.5,"isVisitedPoint":false,"isPossibleToMove":false,"isExplorerOnMe":false,"canGoUp":true,"canGoDown":true,"canGoRight":false,"canGoLeft":true,"levelOfPoint":0},{"Xpos":-0.5,"Ypos":0.5,"isVisitedPoint":false,"isPossibleToMove":false,"isExplorerOnMe":false,"canGoUp":false,"canGoDown":false,"canGoRight":true,"canGoLeft":false,"levelOfPoint":0},{"Xpos":0.5,"Ypos":-0.5,"isVisitedPoint":false,"isPossibleToMove":false,"isExplorerOnMe":false,"canGoUp":true,"canGoDown":false,"canGoRight":true,"canGoLeft":true,"levelOfPoint":0},{"Xpos":-0.5,"Ypos":-0.5,"isVisitedPoint":false,"isPossibleToMove":false,"isExplorerOnMe":false,"canGoUp":false,"canGoDown":false,"canGoRight":true,"canGoLeft":false,"levelOfPoint":0}]},{"loaded":false,"idRegion":5,"isVisitedRegion":false,"visitedPoints":99,"numberOfPoints":99,"levelOfRegion":99,"typeOfRegion":"Wild","structType":0,"structVariant":[99,99,99,99,99,99],"points":[]},{"loaded":false,"idRegion":6,"isVisitedRegion":false,"visitedPoints":99,"numberOfPoints":99,"levelOfRegion":99,"typeOfRegion":"Wild","structType":0,"structVariant":[99,99,99,99,99,99],"points":[]},{"loaded":false,"idRegion":7,"isVisitedRegion":false,"visitedPoints":99,"numberOfPoints":99,"levelOfRegion":99,"typeOfRegion":"Wild","structType":0,"structVariant":[99,99,99,99,99,99],"points":[]},{"loaded":true,"idRegion":8,"isVisitedRegion":true,"visitedPoints":99,"numberOfPoints":21,"levelOfRegion":99,"typeOfRegion":"Wild","structType":0,"structVariant":[1,1,2,2,0,0],"points":[{"Xpos":4.5,"Ypos":2.5,"isVisitedPoint":false,"isPossibleToMove":false,"isExplorerOnMe":false,"canGoUp":false,"canGoDown":false,"canGoRight":false,"canGoLeft":true,"levelOfPoint":0},{"Xpos":3.5,"Ypos":2.5,"isVisitedPoint":false,"isPossibleToMove":false,"isExplorerOnMe":false,"canGoUp":false,"canGoDown":false,"canGoRight":true,"canGoLeft":true,"levelOfPoint":0},{"Xpos":3.5,"Ypos":1.5,"isVisitedPoint":false,"isPossibleToMove":false,"isExplorerOnMe":false,"canGoUp":false,"canGoDown":true,"canGoRight":false,"canGoLeft":false,"levelOfPoint":0},{"Xpos":2.5,"Ypos":2.5,"isVisitedPoint":false,"isPossibleToMove":false,"isExplorerOnMe":false,"canGoUp":false,"canGoDown":true,"canGoRight":true,"canGoLeft":true,"levelOfPoint":0},{"Xpos":1.5,"Ypos":2.5,"isVisitedPoint":false,"isPossibleToMove":false,"isExplorerOnMe":false,"canGoUp":false,"canGoDown":false,"canGoRight":true,"canGoLeft":true,"levelOfPoint":0},{"Xpos":2.5,"Ypos":1.5,"isVisitedPoint":false,"isPossibleToMove":false,"isExplorerOnMe":false,"canGoUp":true,"canGoDown":false,"canGoRight":false,"canGoLeft":false,"levelOfPoint":0},{"Xpos":1.5,"Ypos":1.5,"isVisitedPoint":false,"isPossibleToMove":false,"isExplorerOnMe":false,"canGoUp":false,"canGoDown":true,"canGoRight":false,"canGoLeft":false,"levelOfPoint":0},{"Xpos":0.5,"Ypos":2.5,"isVisitedPoint":false,"isPossibleToMove":false,"isExplorerOnMe":false,"canGoUp":false,"canGoDown":true,"canGoRight":true,"canGoLeft":true,"levelOfPoint":0},{"Xpos":-0.5,"Ypos":2.5,"isVisitedPoint":false,"isPossibleToMove":false,"isExplorerOnMe":false,"canGoUp":false,"canGoDown":true,"canGoRight":true,"canGoLeft":false,"levelOfPoint":0},{"Xpos":0.5,"Ypos":1.5,"isVisitedPoint":false,"isPossibleToMove":false,"isExplorerOnMe":false,"canGoUp":true,"canGoDown":true,"canGoRight":false,"canGoLeft":false,"levelOfPoint":0},{"Xpos":-0.5,"Ypos":1.5,"isVisitedPoint":false,"isPossibleToMove":false,"isExplorerOnMe":false,"canGoUp":true,"canGoDown":false,"canGoRight":false,"canGoLeft":false,"levelOfPoint":0},{"Xpos":4.5,"Ypos":0.5,"isVisitedPoint":false,"isPossibleToMove":false,"isExplorerOnMe":false,"canGoUp":false,"canGoDown":false,"canGoRight":false,"canGoLeft":true,"levelOfPoint":0},{"Xpos":3.5,"Ypos":0.5,"isVisitedPoint":false,"isPossibleToMove":false,"isExplorerOnMe":false,"canGoUp":true,"canGoDown":true,"canGoRight":true,"canGoLeft":false,"levelOfPoint":0},{"Xpos":3.5,"Ypos":-0.5,"isVisitedPoint":false,"isPossibleToMove":false,"isExplorerOnMe":false,"canGoUp":true,"canGoDown":false,"canGoRight":false,"canGoLeft":true,"levelOfPoint":0},{"Xpos":2.5,"Ypos":0.5,"isVisitedPoint":false,"isPossibleToMove":false,"isExplorerOnMe":false,"canGoUp":false,"canGoDown":true,"canGoRight":false,"canGoLeft":true,"levelOfPoint":0},{"Xpos":1.5,"Ypos":0.5,"isVisitedPoint":false,"isPossibleToMove":false,"isExplorerOnMe":false,"canGoUp":true,"canGoDown":true,"canGoRight":true,"canGoLeft":false,"levelOfPoint":0},{"Xpos":2.5,"Ypos":-0.5,"isVisitedPoint":false,"isPossibleToMove":false,"isExplorerOnMe":false,"canGoUp":true,"canGoDown":false,"canGoRight":true,"canGoLeft":false,"levelOfPoint":0},{"Xpos":1.5,"Ypos":-0.5,"isVisitedPoint":false,"isPossibleToMove":false,"isExplorerOnMe":false,"canGoUp":true,"canGoDown":false,"canGoRight":false,"canGoLeft":true,"levelOfPoint":0},{"Xpos":0.5,"Ypos":0.5,"isVisitedPoint":false,"isPossibleToMove":false,"isExplorerOnMe":false,"canGoUp":true,"canGoDown":true,"canGoRight":false,"canGoLeft":false,"levelOfPoint":0},{"Xpos":0.5,"Ypos":-0.5,"isVisitedPoint":false,"isPossibleToMove":false,"isExplorerOnMe":false,"canGoUp":true,"canGoDown":false,"canGoRight":true,"canGoLeft":true,"levelOfPoint":0},{"Xpos":-0.5,"Ypos":-0.5,"isVisitedPoint":false,"isPossibleToMove":false,"isExplorerOnMe":false,"canGoUp":false,"canGoDown":false,"canGoRight":true,"canGoLeft":false,"levelOfPoint":0}]},{"loaded":false,"idRegion":9,"isVisitedRegion":false,"visitedPoints":99,"numberOfPoints":99,"levelOfRegion":99,"typeOfRegion":"Wild","structType":0,"structVariant":[99,99,99,99,99,99],"points":[]},{"loaded":true,"idRegion":10,"isVisitedRegion":false,"visitedPoints":99,"numberOfPoints":99,"levelOfRegion":99,"typeOfRegion":"Wild","structType":0,"structVariant":[99,99,99,99,99,99],"points":[]},{"loaded":false,"idRegion":11,"isVisitedRegion":false,"visitedPoints":99,"numberOfPoints":99,"levelOfRegion":99,"typeOfRegion":"Wild","structType":0,"structVariant":[99,99,99,99,99,99],"points":[]}]}